filebuttons/__init__.py
filebuttons/kv.py
filebuttons-0.3.0.dist-info/licenses/LICENSE.txt
filebuttons-0.3.0.dist-info/METADATA
filebuttons-0.3.0.dist-info/WHEEL
filebuttons-0.3.0.dist-info/entry_points.txt
filebuttons-0.3.0.dist-info/top_level.txt
filebuttons-0.3.0.dist-info/RECORD
