Metadata-Version: 2.4
Name: filebuttons
Version: 0.3.0
Summary: Panel of buttons to launch files into a running IDE.
Author-email: Mark Taylor <mark66547ta2@gmail.com>
Maintainer-email: Mark Taylor <mark66547ta2@gmail.com>
License: MIT License
Project-URL: Homepage, https://github.com/tmarktaylor/filebuttons
Project-URL: Bug Reports, https://github.com/tmarktaylor/filebuttons/issues
Project-URL: Source, https://github.com/tmarktaylor/filebuttons/
Keywords: graphical,user,interface,file,chooser,ide
Classifier: Development Status :: 4 - Beta
Classifier: Intended Audience :: Developers
Classifier: Operating System :: OS Independent
Classifier: Topic :: Software Development
Classifier: Topic :: Utilities
Classifier: License :: OSI Approved :: MIT License
Classifier: Programming Language :: Python :: 3
Classifier: Programming Language :: Python :: 3.9
Classifier: Programming Language :: Python :: 3.10
Classifier: Programming Language :: Python :: 3.11
Classifier: Programming Language :: Python :: 3.12
Classifier: Programming Language :: Python :: 3.13
Classifier: Programming Language :: Python :: 3 :: Only
Requires-Python: >=3.9
License-File: LICENSE.txt
Requires-Dist: kivy
Dynamic: license-file
